{
  "checkpoint": "checkpoints/runpod_v3_no_guide_grid_close_pair_dense_edges_tess15_weighted_probe_20260619/full/latest.pt",
  "manifest": "data/generated/synthetic/cp_training_mix_v5_bp_search225/raw-manifest.jsonl",
  "split": "val",
  "profile": "v4-solid-geometry-replay",
  "threshold": 0.4,
  "offset_radius_px": 3.0,
  "decode": "peak-gated-offset-cluster (evidence_extract.rs parity)",
  "families": {
    "box-pleated": {
      "samples": 174,
      "junctions": 62501,
      "recall": 0.48806,
      "misses": 31997,
      "extras": 584,
      "extras_per_sample": 3.356,
      "clean_rate": 0.2471
    },
    "rabbit-ear-fold-program": {
      "samples": 33,
      "junctions": 1562,
      "recall": 0.9507,
      "misses": 77,
      "extras": 25,
      "extras_per_sample": 0.758,
      "clean_rate": 0.4848
    },
    "search225-tiling": {
      "samples": 93,
      "junctions": 2822,
      "recall": 0.98866,
      "misses": 32,
      "extras": 18,
      "extras_per_sample": 0.194,
      "clean_rate": 0.7419
    },
    "tessellation-fold-program": {
      "samples": 38,
      "junctions": 12849,
      "recall": 0.98763,
      "misses": 159,
      "extras": 4,
      "extras_per_sample": 0.105,
      "clean_rate": 0.9211
    },
    "treemaker-tree": {
      "samples": 174,
      "junctions": 6394,
      "recall": 0.98796,
      "misses": 77,
      "extras": 35,
      "extras_per_sample": 0.201,
      "clean_rate": 0.7529
    }
  },
  "miss_taxonomy": {
    "absent.close_pair": 16915,
    "absent.isolated": 8554,
    "localization.close_pair": 539,
    "localization.isolated": 575,
    "sub_threshold.close_pair": 2924,
    "sub_threshold.isolated": 2835
  },
  "overall": {
    "samples": 512,
    "junctions": 86128,
    "recall": 0.62449,
    "misses": 32342,
    "extras": 666,
    "extras_per_sample": 1.301,
    "clean_rate": 0.5742
  }
}
